word_ending_finder/__init__.py
word_ending_finder/__main__.py
word_ending_finder/cli.py
word_ending_finder/py.typed
word_ending_finder/vie_data.py
word_ending_finder/wef.py
word_ending_finder-0.0.2.dist-info/METADATA
word_ending_finder-0.0.2.dist-info/WHEEL
word_ending_finder-0.0.2.dist-info/entry_points.txt
word_ending_finder-0.0.2.dist-info/licenses/LICENSE
word_ending_finder-0.0.2.dist-info/RECORD
